odoo10_addon_event_phone-10.0.1.0.0-py2.7-nspkg.pth
odoo10_addon_event_phone-10.0.1.0.0.dist-info/top_level.txt
odoo10_addon_event_phone-10.0.1.0.0.dist-info/WHEEL
odoo10_addon_event_phone-10.0.1.0.0.dist-info/RECORD
odoo10_addon_event_phone-10.0.1.0.0.dist-info/metadata.json
odoo10_addon_event_phone-10.0.1.0.0.dist-info/DESCRIPTION.rst
odoo10_addon_event_phone-10.0.1.0.0.dist-info/METADATA
odoo10_addon_event_phone-10.0.1.0.0.dist-info/namespace_packages.txt
odoo/addons/event_phone/__manifest__.py
odoo/addons/event_phone/__init__.py
odoo/addons/event_phone/security/ir.model.access.csv
odoo/addons/event_phone/models/event_registration.py
odoo/addons/event_phone/models/__init__.py
